get_bilibilicover_mcp/__init__.py
get_bilibilicover_mcp-0.1.0.dist-info/WHEEL
get_bilibilicover_mcp-0.1.0.dist-info/entry_points.txt
get_bilibilicover_mcp-0.1.0.dist-info/METADATA
get_bilibilicover_mcp-0.1.0.dist-info/RECORD
