Metadata-Version: 2.3
Name: get-bilibilicover-mcp
Version: 0.1.0
Summary: Add your description here
Requires-Dist: mcp[cli]>=1.12.4
Requires-Python: >=3.13
